ArachneScrapy-0.6.3.dist-info/DESCRIPTION.rst
ArachneScrapy-0.6.3.dist-info/METADATA
ArachneScrapy-0.6.3.dist-info/RECORD
ArachneScrapy-0.6.3.dist-info/WHEEL
ArachneScrapy-0.6.3.dist-info/metadata.json
ArachneScrapy-0.6.3.dist-info/top_level.txt
arachne/__init__.py
arachne/default_settings.py
arachne/endpoints.py
arachne/exceptions.py
arachne/extensions.py
arachne/flaskapp.py
arachne/scrapy_utils.py
arachne/tests/BaseFlaskApp.py
arachne/tests/__init__.py
arachne/tests/test_default_settings.py
arachne/tests/test_endpoints.py
arachne/tests/test_extensions.py
arachne/tests/test_flaskapp.py
arachne/tests/test_scrapy_utils.py
arachne/tests/test_settings.py
