Metadata-Version: 2.0
Name: ArachneScrapy
Version: 0.6.3
Summary: API for Scrapy spiders
Home-page: https://github.com/n3n/arachne
Author: Nonpawit Teerachetmongkol
Author-email: nonpawit.tee@gmail.com
License: BSD
Platform: UNKNOWN
Requires-Dist: Flask (>=0.10.1)
Requires-Dist: Scrapy (>=1.3.0)
Requires-Dist: Twisted (>=15.4.0)
Requires-Dist: six (>=1.10.0)
